sym/SYM.py
sym/__init__.py
sym/app/__init__.py
sym/app/js.py
sym/app/py.py
sym/app/readCollection.py
sym/app/task.py
sym/app/test.py
sym/app/test2.py
sym/app/webhook.py
sym/controller/__init__.py
sym/controller/js.py
sym/controller/local.py
sym/controller/push.py
sym/controller/runWorkflow.py
sym/controller/update.py
sym/controller/workflow.py
sym/source/__init__.py
sym/source/get-clients-erp.py
sym/workflow/__init__.py
sym/workflow/find.py
sym/workflow/workflowTest.py
scrapyomama-0.0.8.dist-info/LICENSE
scrapyomama-0.0.8.dist-info/METADATA
scrapyomama-0.0.8.dist-info/WHEEL
scrapyomama-0.0.8.dist-info/top_level.txt
scrapyomama-0.0.8.dist-info/RECORD
