Metadata-Version: 2.1
Name: scrapyomama
Version: 0.0.8
Summary: Scrap Yo Mama
Home-page: https://github.com/mrsoyer/symtest
Author: Thomas Garcia
Author-email: garciathomas@gmail.com
Classifier: Programming Language :: Python :: 3
Classifier: License :: OSI Approved :: MIT License
Classifier: Operating System :: OS Independent
License-File: LICENSE
Requires-Dist: requestspymongopytzdatetimeuuidpsycopg2google-cloud-pubsubcertifipython-dateutilmomentaiopgfunctions-frameworkpynputpython-dotenvjstyleson
